{
    "3JUdIUVxv2zfJevAidsmQq": 20060,
    "3RJvdtay16xQ_ZgYEsHIy8": 45060,
    "3X414Lh312cfMiVfxwG70Z": 12030,
    "3X414Lh312cfMiVfxwHuWT": 20031,
    "3X414Lh312cfMiVfxwHuWd": 13431,
    "3X414Lh312cfMiVfxwHuGz": 10118,
    "3X414Lh312cfMiVfxwHu4R": 2522,
    "3X414Lh312cfMiVfxwHu0R": 2878,
    "0HIKLxwkUNcnROQims_5Tr": 2159,
    "1CF8dT82jQMdRWHzSzoh8t": 2159,
    "3X414Lh312cfMiVfxwH_bi": 1149,
    "3X414Lh312cfMiVfxwHu1D": 4323,
    "3X414Lh312cfMiVfxwHu2$": 1728,
    "3X414Lh312cfMiVfxwG2yz": 698,
    "18rQOBs86vdKwAL24AiR0p": 1443,
    "2FU7NM7Vr3IBm9jCPWRFOf": 771,
    "0z5x4pFABubaY5uElUM8wU": 1392,
    "3X414Lh312cfMiVfxwG6mB": 3430,
    "3X414Lh312cfMiVfxwHuSf": 2123,
    "1Utb1wR7$FoUgVB5uzF5kz": 1011,
    "0ZydjbAXXE$ftDxw6ws3GB": 637,
    "0ZydjbAXXE$ftDxw6ws3G5": 1485,
    "0ZydjbAXXE$ftDxw6ws3GA": 458,
    "2FU7NM7Vr3IBm9jCPWRF7T": 458,
    "3X414Lh312cfMiVfxwHuTK": 4586,
    "3X414Lh312cfMiVfxwGS94": 501,
    "2Q2eU2TdLOO63FLXtFcYGe": 856,
    "0_mn7CW$ahlhnkUKYh4eBt": 856,
    "3X414Lh312cfMiVfxwGSAC": 6198,
    "3X414Lh312cfMiVfxwHudv": 19798,
    "0ZydjbAXXE$ftDxw6ws3O7": 1693,
    "0ZydjbAXXE$ftDxw6ws3O3": 1080,
    "0B7b8cb5Hdt0pPKkKnmA40": 2015,
    "3mNy1A9VihwKuspfSaSmSs": 2012,
    "3X414Lh312cfMiVfxwG4Gb": 426,
    "26R4GGj8v8EAchpBZVtRyu": 437,
    "2FU7NM7Vr3IBm9jCPWRFNO": 729,
    "3Lu$xo6H6tCcItc73_vOJI": 1434,
    "26R4GGj8v8EAchpBZVtR1R": 639,
    "0G8iBTkv2qAR6U7dZi_e58": 1161,
    "0ZydjbAXXE$ftDxw6ws3Jp": 196,
    "0ZydjbAXXE$ftDxw6ws3Jo": 25,
    "0ZydjbAXXE$ftDxw6ws3JC": 115,
    "0ZydjbAXXE$ftDxw6ws3JE": 206,
    "0ZydjbAXXE$ftDxw6ws3JD": 224,
    "0ZydjbAXXE$ftDxw6ws3J8": 452,
    "0ZydjbAXXE$ftDxw6ws3JA": 564,
    "0ZydjbAXXE$ftDxw6ws3IZ": 175,
    "0ZydjbAXXE$ftDxw6ws3IX": 123,
    "0ZydjbAXXE$ftDxw6ws3IW": 141,
    "0ZydjbAXXE$ftDxw6ws3IY": 207,
    "0ZydjbAXXE$ftDxw6ws3Iz": 308,
    "0ZydjbAXXE$ftDxw6ws3I$": 446,
    "3RJvdtay16xQ_ZgYEsHJZi": 21391,
    "2jDf5z0IUNguvW$4sahgUd": 2111
}